ccsr/__init__.py
ccsr/__main__.py
ccsr/monkey_patch.py
ccsr/hook_utils/__init__.py
ccsr/hook_utils/custom_config.py
ccsr/hook_utils/dependencies.py
cookiecutter_scientific_research-1.0.5.dist-info/entry_points.txt
cookiecutter_scientific_research-1.0.5.dist-info/licenses/LICENSE
cookiecutter_scientific_research-1.0.5.dist-info/WHEEL
cookiecutter_scientific_research-1.0.5.dist-info/METADATA
cookiecutter_scientific_research-1.0.5.dist-info/RECORD
