Metadata-Version: 2.4
Name: cookiecutter-scientific-research
Version: 1.0.5
Summary: A logical, reasonably standardized but flexible project structure for doing and sharing scientific research.
Keywords: cookiecutter,template,science,research,reproducible-research,project-structure
Author-email: Wenjie Xu <wenjie.xu.cn@outlook.com>
Requires-Python: >=3.9
Classifier: Development Status :: 5 - Production/Stable
Classifier: Intended Audience :: Developers
Classifier: Intended Audience :: Science/Research
Classifier: License :: OSI Approved :: MIT License
Classifier: Programming Language :: Python :: 3
Classifier: Programming Language :: Python :: 3.9
Classifier: Programming Language :: Python :: 3.10
Classifier: Programming Language :: Python :: 3.11
Classifier: Programming Language :: Python :: 3.12
Classifier: Programming Language :: Python :: 3.13
Classifier: Topic :: Scientific/Engineering
Classifier: Topic :: Scientific/Engineering :: Artificial Intelligence
License-File: LICENSE
Requires-Dist: click
Requires-Dist: cookiecutter
Requires-Dist: tomlkit
Requires-Dist: flit_core ; extra == "dev"
Requires-Dist: ansi2html ; extra == "dev"
Requires-Dist: black ; extra == "dev"
Requires-Dist: build ; extra == "dev"
Requires-Dist: flake8 ; extra == "dev"
Requires-Dist: isort ; extra == "dev"
Requires-Dist: pytest ; extra == "dev"
Requires-Dist: twine ; extra == "dev"
Requires-Dist: mkdocs ; extra == "docs"
Requires-Dist: mkdocs-material ; extra == "docs"
Requires-Dist: pytest-cov ; extra == "test"
Requires-Dist: hypothesis ; extra == "test"
Project-URL: Documentation, https://github.com/waynexucn/cookiecutter-scientific-research/blob/master/README.md
Project-URL: Issues, https://github.com/waynexucn/cookiecutter-scientific-research/issues
Project-URL: Source Code, https://github.com/waynexucn/cookiecutter-scientific-research/
Provides-Extra: dev
Provides-Extra: docs
Provides-Extra: test
